dictionary/__init__.py
dictionary/dictionary.py
aaaa_dictionary-3.0.1.dist-info/METADATA
aaaa_dictionary-3.0.1.dist-info/WHEEL
aaaa_dictionary-3.0.1.dist-info/top_level.txt
aaaa_dictionary-3.0.1.dist-info/RECORD
