Metadata-Version: 2.1
Name: aaaa-dictionary
Version: 3.0.1
Summary: UNKNOWN
Author: Barış Tiftik
License: UNKNOWN
Platform: UNKNOWN
Requires-Python: >=3.8
Requires-Dist: requests (>=2.23.0)
